lithiumpythonsdk/__init__.py
lithiumpythonsdk/lithium_bulk.py
lithiumpythonsdk/lithium_rest_v1.py
lithiumpythonsdk/lithium_rest_v2.py
lithium_python_sdk-0.1.1.dist-info/METADATA
lithium_python_sdk-0.1.1.dist-info/WHEEL
lithium_python_sdk-0.1.1.dist-info/top_level.txt
lithium_python_sdk-0.1.1.dist-info/RECORD
